[
  {
    "school": "さくら小",
    "grades": [],
    "themes": [
      "まち",
      "環境",
      "福祉",
      "平和",
      "防災",
      "食",
      "まちづくり"
    ],
    "info_keywords": [],
    "grade_themes": [],
    "raw_preview": "さくら小学校＜総合的な学習の時間 年間計画＞３年４年５年６年４月学ぼう私たちの町1 ～校区について～ ・総合学習とは。 ・意見交流をしよう。 ・校区探検をしよう。 日本全国旅物語 ・都道府県を知ろう。 ・都道府県かるたを作ろう。 ・おすすめ旅物語を作ろう。 つながる・つなげる～人とつながろう～・兵庫県多可郡多可町について調べる。・林間の目標、計画を立てる。紡いで 繋いで～防災教育～・防災教育・我が家の防災バッグを考えよう５月６月７月８月学ぼう私たちの町２ ～様々な施設～ ・スーパーマーケットや商店街、工場などを見学する。 ・社会見学から、課題を見つけ調べる。 ・調べたことを分かり やすく発表する。 ・意見交流をする。 ・消防署を見学する。 環境にやさしいまち物語 ・自然環境問題について調べよう。 ・SDGｓ自分たちができる環境にやさしいまちづくりについてまとめる。 つながる・つなげる～社会とつながろう～・日本の食料生産について考える。・日本の工業生産について考える。・自分で課題を決め、 調べる。紡いで 繋いで～平和学習～・世界の平和について考える。・世界の様々な国による、戦争や平和に対する考え方の違いについて考える。・調べまとめた結果を発表する。９月10月11月12月１月学ぼう私たちの町3・昔の暮らしから、 課題を決め、調べる。 ・分かりやすく発表 できる方法を考え、 まとめる。 ・調べたことを発表 する。 人にやさしいまち物語 ・福祉について考える。 ・バリアフリー体験を する。 ・校区のバリアフリーについて調査する。 ・調べた結果をわかり やすく発表できる 方法を考え、まとめる。 ・まとめた結果を交流 する。 つながる・つなげる～世界とつながろう～ ・世界とのつながりについて考える。・自分で課題を決め調べる。自分にできることは何か考え、発表する。紡いで 繋いで～キャリア教育～・自分の将来なりたい仕事について調べる。・自分の将来像を考える。・卒業式について考える。２月３月",
    "text_length": 851,
    "file": "【さくら小】⑤R8総合的な学習の時間（年間計画）（さくら小）_sanitized.docx",
    "ext": ".docx",
    "extract_ok": true
  },
  {
    "school": "さつき",
    "grades": [],
    "themes": [],
    "info_keywords": [],
    "raw_preview": "",
    "file": "【さつき】⑤「総合的な学習」の全体計画2_sanitized.pdf",
    "ext": ".pdf",
    "extract_ok": false
  },
  {
    "school": "さつき",
    "grades": [],
    "themes": [],
    "info_keywords": [],
    "raw_preview": "",
    "file": "【さつき】⑤「総合的な学習」の全体計画_sanitized.pdf",
    "ext": ".pdf",
    "extract_ok": false
  },
  {
    "school": "よつば小",
    "grades": [],
    "themes": [],
    "info_keywords": [],
    "raw_preview": "",
    "file": "【よつば小】⑤総合的な学習の時間全体計画_sanitized.xls",
    "ext": ".xls",
    "extract_ok": false
  },
  {
    "school": "佐太小",
    "grades": [],
    "themes": [
      "地域",
      "環境",
      "国際",
      "福祉",
      "平和",
      "人権",
      "食",
      "農",
      "文化",
      "情報"
    ],
    "info_keywords": [],
    "grade_themes": [],
    "raw_preview": "段落フォント 標準の表 リストなし ヘッダー フッター 吹き出し リスト段落 強調斜体 見出しマップ 見出しマップ 吀椀洀攀猀 一攀眀 刀漀洀愀渀 匀礀洀戀漀氀 爀椀愀氀 攀渀琀甀爀礀 椀渀挀栀漀 漀琀栀椀挀 爀椀愀氀 唀渀椀挀漀搀攀 漀琀栀椀挀 椀最栀琀 圀椀渀最搀椀渀最猀 愀洀戀爀椀愀 愀琀栀 鬰鰰鴰鸰 巿懿揿擿旿黿鿿 嬀尀笀 渀渄椄鸀舀犀 唀渀欀渀漀眀渀 佔最倈 剞匀匬 圍一坴 奎倀奾居 慼栀搡洀攃 桲渀椂 樛圀橩 渹挀漓 漩谀漭謀潖蜀潿鰀灏夀煀 獉猀獖砈頀礻 祠縀祬 笶縀簻脀籽 繋娀繐 聻搀脢 荍戀荑需荣 蜺昀褆 轡樀逨 鍯茀鍲戀错儀锺 镭戀霘 饇鐀騈 鬔 鴒踀鼕一鼳謀齑 「総合的な学習の時間」の全体計画 本校の教育目標 自ら考え行動する子どもの育成 子どもたちが心から笑顔になれる学校 ・笑顔であいさつのできる子 ・人の話をしっかり聴ける子 ・よく考え、行動できる子 ・いっしょうけんめいに勉強し、思いっきり遊ぶ子 ・たがいに認め合い、助け合う子 学習課題 地域の人々の暮らし 福祉・ボランティア 水とゴミ 福祉・ボランティア 環境問題 米づくり 人権・平和学習 国際理解 学習対象 商店で働く人々 梅香苑の高齢者 身の周りのバリアフリー とボランティア活動 身近な環境問題 地域の農家経験者 大阪の戦跡や戦争体験 〇広島平和公園 身近な在日外国人とその文化 学習事項 ・商店・飲食店の特徴や労働の姿 ・高齢者の方へのボランティア活動 ・町の中のバリアフリーと アイマスク体験 ・淀川の環境保全と浄水場 の役割 ・地球の環境問題を考える ・食生活を支える、農作物を育てる農家の思い についての理解を深める ・平和を願う人々の思い ・韓国の文化の理解と体験 教科等との関連 国語 伝え合う力・思考力・想像力・言語感覚 社会 我が国の国土と歴史。社会生活についての理解 算数 数量や図形についての知識・技能 理科 問題解決の能力と自然を愛する心情 音楽 音楽を愛好する心情と感性、豊かな情操 図工 造形的な創造活動の基礎的な能力 家庭 自らの生活をよりよくしようとする実践的な態度 体育 楽しく明るい生活を営む態度 道徳 道徳的な心情、判断力、実践意欲と態度 外国語 言語や文化についての理解 特別活動 自己の生き方についての考えを深め、自己を生かす能力 保護者、教職員の願い 思いやりのある子ども 自ら学ぼうとする子ども 児童の実態 素直でのびのびした子どもが多い 真面目であるが、消極的な傾向が強い 地域の様子 校区は淀川河川敷のそばにある住宅地域で、教育的関心が高く、地域の協力も大きい 総合的な学習の時間の目標 地域・社会の特色や目的課題等に応じた体験的な学習活動を通して、主体的に生きる子どもを育てる 総合的な学習で育てたい力 課題設定 地域社会の人々や事物・自然と親しみを持ってかかわり、活動できる力 課題追求 自ら学び、考え、主体的に取り組もうとする力 問題解決 自分を見つめ、発見した問題や課題をやり遂げていく力 表現活動 自らの思いや願いを表現・伝達しあう力 指導方法 ・児童が課題意識を生みだす支援 ・児童が課題追求のなかで試行錯誤できる体験活動の工夫 ・グループによる共同的な学習活動の充実 ・収集した情報の言語化の支援 指導体制 ・教職員が一体となった指導とサポートの体制の確立する ・地域や外部人材と連携し支援・協力体制を確立する 学習の評価の観点 ・課題を発見し主体的に活動する ・計画を立てて意欲的に課題を解決する態度 ・互いのよさを認め合い、協力し合う ・自分の考えや思いをまとめ分かりやすく表現する 莣卤撃撃撃 沌沌沌沌 乨鼳唀 蒣梣葋梣 梣葋萀 蒣蒣蒣梣 薥曂帀 詴榮帀 怃悄懿 崀熄帀熄愀 崀熄帀熄愀 悄埿鱄 怀悄懿 崀熄帀熄愀 礀乴鼳 礀乴鼳 礀乴鼳 楍牣獯景 卍潗摲潄 捯浵湥 伊藤仁 タイトル",
    "text_length": 1625,
    "file": "【佐太小】⑤「総合的な学習の時間」の全体計画（佐太小）_sanitized.doc",
    "ext": ".doc",
    "extract_ok": true
  },
  {
    "school": "佐太小",
    "grades": [],
    "themes": [],
    "info_keywords": [],
    "raw_preview": "",
    "file": "【佐太小】⑤総合的な学習の時間全体計画_sanitized.xls",
    "ext": ".xls",
    "extract_ok": false
  },
  {
    "school": "八雲中",
    "grades": [],
    "themes": [],
    "info_keywords": [],
    "grade_themes": [],
    "raw_preview": "\\*02020603050405020304Times New Roman;\\*05000000000000000000Wingdings;\\*02020609040205080304lr ｾｩ\\*MS Mincho;\\*020b0609070205080204lr SVbN\\*MS Gothic;\\*02040604050505020304Century;\\*02040503050406030204Cambria Math;\\*00000000000000000000lr oSVbN;\\*020f0600000000000000HGﾛｺﾞｼｯｸM-PRO;\\*02020700000000000000UD fW^ ｳﾈﾌ NK-B;\\*00000000000000000000@lr SVbN;@lr oSVbN;\\*00000000000000000000@lr ｾｩ;@UD fW^ ｳﾈﾌ NK-B;@HGﾛｺﾞｼｯｸM-PRO;\\*02020603050405020304Times New Roman;\\*020b0609070205080204lr SVbN\\*MS Gothic;\\*020b0604020202020204Arial;\\*02020603050405020304Times New Roman;\\*02020603050405020304Times New Roman;\\*02020609040205080304lr ｾｩ\\*MS Mincho;\\*02040604050505020304Century;\\*02020603050405020304Times New Roman;Times New Roman CE;Times New Roman Cyr;Times New Roman Greek;Times New Roman Tur;Times New Roman (Hebrew);Times New Roman (Arabic);Times New Roman Baltic;Times New Roman (Vietnamese);MS Mincho Western\\*MS Mincho;MS Mincho CE\\*MS Mincho;MS Mincho Cyr\\*MS Mincho;MS Mincho Greek\\*MS Mincho;MS Mincho Tur\\*MS Mincho;MS Mincho Baltic\\*MS Mincho;MS Gothic Western\\*MS Gothic;MS Gothic CE\\*MS Gothic;MS Gothic Cyr\\*MS Gothic;MS Gothic Greek\\*MS Gothic;MS Gothic Tur\\*MS Gothic;MS Gothic Baltic\\*MS Gothic;Century CE;Century Cyr;Century Greek;Century Tur;Century Baltic;Cambria Math CE;Cambria Math Cyr;Cambria Math Greek;Cambria Math Tur;Cambria Math Baltic;Cambria Math (Vietnamese);MS PGothic Western;MS PGothic CE;MS PGothic Cyr;MS PGothic Greek;MS PGothic Tur;MS PGothic Baltic;HGMaruGothicMPRO Western;HGMaruGothicMPRO CE;HGMaruGothicMPRO Cyr;HGMaruGothicMPRO Greek;HGMaruGothicMPRO Tur;HGMaruGothicMPRO Baltic;@MS Gothic Western;@MS Gothic CE;@MS Gothic Cyr;@MS Gothic Greek;@MS Gothic Tur;@MS Gothic Baltic;@MS PGothic Western;@MS PGothic CE;@MS PGothic Cyr;@MS PGothic Greek;@MS PGothic Tur;@MS PGothic Baltic;@MS Mincho Western;@MS Mincho CE;@MS Mincho Cyr;@MS Mincho Greek;@MS Mincho Tur;@MS Mincho Baltic;@HGMaruGothicMPRO Western;@HGMaruGothicMPRO CE;@HGMaruGothicMPRO Cyr;@HGMaruGothicMPRO Greek;@HGMaruGothicMPRO Tur;@HGMaruGothicMPRO Baltic;Times New Roman CE;Times New Roman Cyr;Times New Roman Greek;Times New Roman Tur;Times New Roman (Hebrew);Times New Roman (Arabic);Times New Roman Baltic;Times New Roman (Vietnamese);MS Gothic Western\\*MS Gothic;MS Gothic CE\\*MS Gothic;MS Gothic Cyr\\*MS Gothic;MS Gothic Greek\\*MS Gothic;MS Gothic Tur\\*MS Gothic;MS Gothic Baltic\\*MS Gothic;Arial CE;Arial Cyr;Arial Greek;Arial Tur;Arial (Hebrew);Arial (Arabic);Arial Baltic;Arial (Vietnamese);Times New Roman CE;Times New Roman Cyr;Times New Roman Greek;Times New Roman Tur;Times New Roman (Hebrew);Times New Roman (Arabic);Times New Roman Baltic;Times New Roman (Vietnamese);Times New Roman CE;Times New Roman Cyr;Times New Roman Greek;Times New Roman Tur;Times New Roman (Hebrew);Times New Roman (Arabic);Times New Roman Baltic;Times New Roman (Vietnamese);MS Mincho Western\\*MS Mincho;MS Mincho CE\\*MS Mincho;MS Mincho Cyr\\*MS Mincho;MS Mincho Greek\\*MS Mincho;MS Mincho Tur\\*MS Minch",
    "text_length": 18322,
    "file": "【八雲中】⑤R8総合的な学習の時間の全体計画_sanitized.rtf",
    "ext": ".rtf",
    "extract_ok": true
  },
  {
    "school": "八雲小",
    "grades": [],
    "themes": [
      "地域",
      "環境",
      "国際",
      "福祉",
      "平和",
      "人権",
      "農",
      "健康",
      "文化",
      "情報",
      "探究"
    ],
    "info_keywords": [
      "情報活用",
      "ICT",
      "タブレット"
    ],
    "grade_themes": [],
    "raw_preview": "○地域の様子・校区は、淀川河川公園や下島公園があり、自然環境に恵まれた地域・保護者・地域住民は本校教育に協力的○児童の実態・素直で明るい子が多い・だんじりなど地域との関わりがある一方で、その他では薄い面が見られる○保護者・教職員の願い・善悪の判断のできる子ども・思いやりの心をもった子ども・自分の考えをはっきり言える子ども・ねばり強く最後までがんばれる子ども○地域の様子・校区は、淀川河川公園や下島公園があり、自然環境に恵まれた地域・保護者・地域住民は本校教育に協力的○児童の実態・素直で明るい子が多い・だんじりなど地域との関わりがある一方で、その他では薄い面が見られる○保護者・教職員の願い・善悪の判断のできる子ども・思いやりの心をもった子ども・自分の考えをはっきり言える子ども・ねばり強く最後までがんばれる子ども７．総合的な学習の時間全体計画憲法教育基本法学校教育法学習指導要領府・市の教育方針憲法教育基本法学校教育法学習指導要領府・市の教育方針学校教育目標健康で、心豊かに、たくましく生きる子“笑顔で”「時を守り 場を清め 礼を正す」学校教育目標健康で、心豊かに、たくましく生きる子“笑顔で”「時を守り 場を清め 礼を正す」 研究主題自ら考えたことを表現して学びあう子の育成～タブレットを活用して伝え合う学びを目指して～研究主題自ら考えたことを表現して学びあう子の育成～タブレットを活用して伝え合う学びを目指して～総合的な学習の時間の目標 探究的な見方・考え方を働かせ、横断的・総合的な学習を行うことを通して、よりよく課題を解決し、自己の生き方を振り返り、自らの生活や行動や学ぶことの意味、自分の将来について考えていくための資質・能力を次のとおり育成することをめざす。(1) 探究的な学習の過程において、課題の解決に必要な知識及び技能を身に付け、課題に関わる概念を形成し、探究的な学習のよさを理解するようにする。(2) 実社会や実生活の中から問いを見いだし、自分で課題を設定し、解決の手順や方法を考え、見通しをもって取り組み、比較・関連して考えたり、相手や目的に応じてまとめたり発表したりすることができるようにする。(3) 探究的な学習に主体的・協働的に取り組むことを通して、自らの生活のあり方を見直したり、将来への夢や希望をもったりすることができるよう、互いのよさを生かしながら、積極的に社会に参画しようとする態度を養う。総合的な学習の時間の目標 探究的な見方・考え方を働かせ、横断的・総合的な学習を行うことを通して、よりよく課題を解決し、自己の生き方を振り返り、自らの生活や行動や学ぶことの意味、自分の将来について考えていくための資質・能力を次のとおり育成することをめざす。(1) 探究的な学習の過程において、課題の解決に必要な知識及び技能を身に付け、課題に関わる概念を形成し、探究的な学習のよさを理解するようにする。(2) 実社会や実生活の中から問いを見いだし、自分で課題を設定し、解決の手順や方法を考え、見通しをもって取り組み、比較・関連して考えたり、相手や目的に応じてまとめたり発表したりすることができるようにする。(3) 探究的な学習に主体的・協働的に取り組むことを通して、自らの生活のあり方を見直したり、将来への夢や希望をもったりすることができるよう、互いのよさを生かしながら、積極的に社会に参画しようとする態度を養う。内容第３学年第４学年第５学年第６学年他教科等で身に付けた資質・能力探求課題（例）地域の人々の暮らし福祉・ボランティア環境問題人権（国際理解）・平和学習探求課題の解決を通して育成をめざす具体的な資質・能力知識及び技能・地域に住む人びとの技や生き方や思い、仕事にかける思いが分かる。・地域にあるものや場所と、地域の人との関わりや自分とのつながりが分かる。・障がい者や高齢者本人や当事者を支える周りの人々の思いや願いが分かる。・都市部と農村部の自然環境の比較をし、その違いが分かる。・日本や世界の環境問題の現状とそれに関わる人々の生き方や思いが分かる。・平和を願う人々の思いや地球全体を通して自然・文化等を守ろうとする人々の思いや願いが分かる。・世界の国々の文化や習慣などを調べ、それぞれの国の生活の様子や日本との関わりが分かる。情報を比較・分類するなど、探究の過程に応じた技能を身に付けている。情報を比較・分類・関連付けるなど、探究の過程に応じた技能を身に付けている。思考力、判断力、表現力等課題の設定自分の関心から地域についての課題を設定し、解決方法を考えて追究している。地域の人々等の思いをふまえて課題を設定し、解決方法や手順を考え、見通しを持って追究している。情報の収集目的に応じた対象を決め、自分たちの身近なところから情報を集めている。目的に応じて手段を選択し、情報を収集したり、必要な情報を選んだりしている。整理・分析問題状況における事実や関係を、事象を比較したり分類したり、数量などで客観的に比較したりして、特徴を見付けている。視点を明確にして問題状況における事実や関係と、整理した情報を関連付けたり、多面的に考察したりして理解し、多様な情報の中にある特徴を見付けている。まとめ・表現相手に応じてわかりやすくまとめ、表現している。相手や目的、意図に応じ、工夫してまとめ、表現している。振り返り学習したことをふり返り、生活に生かそうとしている。学習の仕方をふり返り、学習や生活に生かそうとしている。学びに向かう力、人間性等主体性課題の解決に向け、目的意識をもって意欲的に取り組んでいる。課題意識をもって、自分なりの方法を工夫しながら探究活動に取り組んでいる。協働性課題解決に向けて、身近な人と力を合わせて探究活動に取り組んでいる。課題解決に向けて、他者と協働して探究活動に取り組み、その大切さに気付いている。自己理解自分のよさや自分にできることに気付いている。探究活動を通して、自分の生活を見直し、自分の特徴を理解しようとしている。他者理解自分と異なる意見や考えがあることに気付き、相手の立場を理解する。異なる意見や他者の考えを受け入れ尊重しながら、探究活動に取り組んでいる。社会参画自分と地域とのつながりに気付き、地域の活動に参加しようとしている。探究活動を通して、自分と実生活・実社会の問題の解決に取り組もうとする。教科等を越えたすべての学習の基盤となる資質・能力情報活用能力言語能力情報・情報技術を活用する学習活動（情報手段の主体的な操作を習得し、情報や情報手段を主体的に選択し、活用できるよう配慮する）他者と協働して課題を解決しようとする学習活動言語により分析し、まとめたり表現したりするなどの学習活動考えるための技法の活用（比較、分類、関連付け、順序付け、多面的・多角的に見る、理由付け、見通す、具体化、抽象化、構造化 等）学習活動指導方法指導体制学習の評価・地域や児童の実態を踏まえ、探求課題を設定する。・地域の人、もの、ことを生かした学習活動を行う。・学習の成果を保護者・地域に公表する。・体験を通した情報収集の重視・体験で獲得した情報の言語化・教科との関連的な指導の重視・学年全体やグループでの活動等、協働的な学習活動の充実・ICT活用・",
    "text_length": 4235,
    "file": "【八雲小】⑤総合的な学習の時間全体計画_sanitized.docx",
    "ext": ".docx",
    "extract_ok": true
  },
  {
    "school": "八雲東小",
    "grades": [],
    "themes": [
      "地域",
      "環境",
      "国際",
      "福祉",
      "平和",
      "防災",
      "健康",
      "文化",
      "伝統",
      "情報"
    ],
    "info_keywords": [
      "情報活用",
      "グラフ"
    ],
    "grade_themes": [],
    "raw_preview": "見出し 見出し 段落フォント 標準の表 リストなし フッター ページ番号 ヘッダー 吀椀洀攀猀 一攀眀 刀漀洀愀渀 匀礀洀戀漀氀 爀椀愀氀 椀渀挀栀漀 漀琀栀椀挀 攀渀琀甀爀礀 椀最栀琀 愀洀戀爀椀愀 愀琀栀 鬰鰰鴰鸰 巿懿揿擿旿黿鿿 嬀尀笀 唀渀欀渀漀眀渀 啗鬀娱茀婟嬏 樞鈀渎瀾鐀甦琀砌 籁紨縀聇 茐匀荱攀萍 葨阀蜶 襶娀譧 鍛蠀鑨 総合的な学習の時間 全体計画 学校教育目標 自ら学ぶ意欲を持ち、心豊かで、たくましく生きる子どもの育成 児童の実態 ・明るく活発で仲良くできる ・地域に関する学習に意欲的に取 り組むことができる ・自分の思いを表現することがやや苦手である ・しっかり考え、粘り強くやりぬくことがやや苦手である 保護者の願い ・自分の目標を持ち主体的に 活動してほしい ・誰に対しても思いやりの気 持ちを持って行動してほしい 目 標 自ら考え、学びあう子どもをめざして 地域の願い ・思いやりの心や学力を身につけ、地域と共に成長してほしい 地域の実態 ・学校ボランティアなどに協力していただける人材がいらっしゃる 国際理解に関する学習 地域に関する学習 防災・福祉に関する学習 環境に関する学習 情報に関する学習 歴史・文化・芸術などに関する学習 平和に関する学習 児童の興味・関心に基づく課題に関する学習 育てようとする資質や能力及び態度 学び方やものの考え方を身に付け、主体的に問題を解決することができる力 地域の人々と共に地域を大切にしていく豊かな心 学びの中で身につけた力を生かし、よりよく確かに生きる態度 自ら学ぶ 自ら進んで考え行動できる・課題をもって追究する 思いやりの心をもつ 自分をしっかり見つめ、自分も他者も大切にする・友だちと協力しあい高めあう 生きる力を身につける 自分の意見をしっかり持ち、発表できる・状況に応じて判断できる 指導体制 ・学校教育計画 グランドデザイン への位置付け。 ・研究部と学年会と学年の総合的な学習係による活動の計画と運営。 ・地域の学習材の見出しと協力していただける施設、事業所のピックアップ。 ・学年単位での活動を支える教職員による支援体制の確立 学習の評価 学習カード ・活動計画 ・自己評価 ・相互評価 ・課題設定の理由 ・学習計画 ・調査方法 ・まとめの方法 活動観察 ・活動の様子 発言、つぶやき ・話し合いへの関わり ・課題設定 ・作品の工夫 ・完成作品 ・発表計画 ・発表態度 ・発表内容 指導方法 協同的な学習活動の充実 観察・実験やレポートの作成など知識・技能を活用する学習指導 問題解決的な学習指導 探求的な活動への取り組み 学習活動 個人やグループの課題を設定して追究し、自己の生き方を見つめる学習 コンピュータ操作、情報活用能力を高める学習 外国の文化・伝統にふれ親しむ学習 高齢者、障がい者とふれ合う学習 身近な環境問題に気付く学習 各教科等との関連 国語 ・自分の考えや気持ちをことばで表現する。 ・相手が伝えたいことを適切に聞き取る。 社会 ・社会事象に関心を持ちすすんで調べる。 ・資料を読み取ったり 関係付けて考察したりする。 算数 ・課題を整理し 筋道をたてて考える。 ・目的に応じて 図やグラフで表現する。 ・適切な方法で測定する。 理科 ・自然の事象に関心を持ち すすんで調べる。 ・見通しをもって課題を検証したり 新たな課題を設定したりする。 体育 ・健康 安全に関する知識 音楽 ・日本や外国の文化の理解 図工 ・日本や外国の文化の理解 家庭 ・日常生活に必要な知識理解 生活を工夫しようとする実践的態度 道徳・特活・自分自身や自分の生活について考える。 ・具体的な活動を通して 自立への基礎を培う。 外国語 ・外国語によるコミュニケーションにおける見方・考え方 家庭・地域社会との連携 ・地域人材バンクの 学習活動への参加 ・地域への情報発信の場 学校だより、通信、学級懇談会等 近隣の学校園等との連携 ・近隣の認定こども園等の幼児との交流 ・第一中学校生徒会との交流 鞣禅孭孭孭孹孹孹孹孹祉祛 皓幪幪 閭簀必必必必必 閲杽乽 悄埿鱄 悄埿鱄 悄埿鱄 鶄圀扄 悄埿鱄 肄埽灄 悄埿鱄 悄埿鱄 楍牣獯景 卍潗摲潄 捯浵湥 八雲東小教職員 梶原康弘 学校の教育目標 タイトル 学校の教育目標 学校の教育目標",
    "text_length": 1810,
    "file": "【八雲東小】⑤「総合的な学習の時間」の全体計画_sanitized.doc",
    "ext": ".doc",
    "extract_ok": true
  },
  {
    "school": "守口小",
    "grades": [],
    "themes": [
      "地域",
      "環境",
      "SDGs",
      "福祉",
      "平和",
      "人権",
      "情報",
      "探究"
    ],
    "info_keywords": [
      "アンケート"
    ],
    "grade_themes": [],
    "raw_preview": "守口市立守口小学校 総合的な学習の時間 全体計画 児童の実態 ・素直でまじめに取り組む 児童が多い一方、自己 肯定感が低い ・体験的活動の不足 ・自分で考え粘り強く取り 組む姿勢に課題 | 学校教育目標 「自ら学ぶ意欲にあふれ、共に高めあい、心豊かで未来を切り拓く子どもの育成」 | 地域の実態 ・旧街道の宿場町 ・旧住宅地と高層住宅群 ・中小工場の密集地 ・大手家電メーカー めざす学校像 | めざす子ども像 ◇人権を尊重し、安全・安心が守られる学校 ◇子どもの笑顔があふれ、みんなで伸びる学校 ◇学校・家庭・地域が連携・協力し、子どもを育てる学校 | ◇笑顔であいさつができる子 ◇人の話を最後まで聴く子 ◇自分でしっかり考えて行動できる子 | ◇互いの違いを認め合い 高め合える子 ◇ねばり強く取り組む子 総合的な学習の時間 第１の目標 地域の願い ・地域行事等に積極的に参加してほしい ・豊かな人間性を身に着けてほしい 保護者の願い ・主体的な行動 ・思いやりの気持ち ・基礎・基本の習得 ・安全に対する意識の 育成 | 本校の総合的な学習の時間の目標 探求的な見方・考え方を働かせ、身近な生活的課題や地域についての横断的・総合的な学習を行うことを通して、協働した調査と論理的な分析によって課題を解決し、自己の生き方を考えることができるようにするために、以下の資質・能力を育成する。 （１）探求的な学習の過程において、課題の解決に必要な知識及び技能を身に着け、地域のよさや諸課題に気づくととも に、それを支える人々の努力や願いがあることや、探求的な学習のよさを理解するようにする。 （２）身近な生活的課題や地域の中から問いを見いだし、自分で課題を立て、手段を選択して情報を集め、他教科等の学習を活用しながら整理・分析して、目的に応じてまとめ・表現することができるようにする。 （３）探求的な学習に主体的・協働的に取り組むとともに、互いのよさを認め合いながら、積極的に社会に参画しようとする態度を養う。 | 地域の願い ・地域行事等に積極的に 参加してほしい ・豊かな人間性を身に着 けてほしい 総合的な学習の時間の内容 | 他教科等で身に着けた資質・能力 学年 | 3年 | 4年 | 5年 | 6年 テーマ | 地域 | 福祉 | 環境 | 平和 探求課題 | 郷土のよさとそれを支える人々の努力や願い | 身近な生活的課題とバリアフリーやユニバーサルデザイン | 身近な環境問題とSDGs | 戦争によってもたらされる惨禍や核兵器の脅威への理解、世界平和についての考察 を行う 探求課題の解決を通して育成を目指す資質・能力 | 知識及び技能 | 知識 | 地域のよさや地域に住む人々の思いが分かる。 | 社会における障害と、それを取り除く取り組みが分かる。 | 身近にも環境問題があることや、SDGsについて分かる。 | 子どもたちが戦争などの平和問題を多面的・多角的に理解できる。 技能 | アンケートやインタビューを相手や場面に応じて適切に実施する。 | 情報の種類や今後の見通しを踏まえ、適切な方法を用いて情報を整理する。 探求的な学習 のよさの理解 | 地域を大切にしたいという自分たちの思いの深まりは、地域のよさや人々の思いについて探求的に学んだことによる成果であると気づく。 | 社会における障害への見方の深まりは、身近な生活的課題等について探求的に学んだことによる成果であると気づく。 | 環境問題への認識の深まりは身近な環境問題とSDGsについて探求的に学んだことによる成果であると気づく。 | 自分が主役となり、自分で考え、行動し、結論を出す学習となるよう主体性を養い、アウトプットすることでコミュニケーションを図ることの有用性に気づく。 思考力・判断力・表現力等 | 課題の設定 | 自分の生活や身近な地域の中から問いを見出し、課題を立てる。 | より広い範囲についての課題を自分で立て、解決の方法や手順を見通しをもって考える。 情報の収集 | 目的に応じて対象や手段を選択し、自分たちの身近なところから情報を集める。 | 目的に応じて対象や手段を選択・工夫し、効率的に情報を収集したり、見通しをもって蓄積したりする。 整理・分析 | 事実をとらえるために比較・分類・関連付けるなどして、情報を整理・分析する。 | 考えるための技法や思考ツールを効果的に用いて情報を整理・分析し、課題に即して多面的に考察する判断材料とする。 まとめ・表現 | 自分の伝えたいことを明確にし、方法を工夫しながらまとめ・表現する。 | 自分の意見や立場を明確にし、相手や目的に応じてわかりやすくまとめ・表現するとともに、学習の仕方を振り返り、他の学習や生活に生かす。 学びに向かう力・人間性等 | 主体性・ 協働性 | 自分なりの目標をもって、身近な人と力を合わせて探究活動に意欲的に取り組む。 | 自分なりに課題意識をもって、身近な人と力を合わせて方法を工夫しながら探究活動に取り組む。 自己理解・ 他者理解 | 探究活動の中で、自分や他者の意見や考えにそれぞれよさがあることに気づく。 | 探究活動の中で、自分や他者の意見や考えのよさを認め合って、それを生かしながら学び合う。 将来展望・ 社会参画 | 身近な地域や生活的課題に関心を持ち、できることを探すなど自ら関わろうとする。 | より広い範囲についての課題に関心を持ち、必要なことやできることを検討して実践に移そうとする。 【学習活動】 | 【指導方法】 | 【指導体制】 | 【学習の評価】 ・地域の実態、児童の実態を踏まえ、 探求課題を設定する。 ・多様な人々と協働して解決する必要のある 探求課題を設定する。 ・思考ツールを取り入れて整理・分析する。 | ・体験活動を重視する。 ・各教科等と関連を重視した指導をう。 ・SDGsを意識し持続可能な社会について 考えられる指導の工夫をする。 | ・地域資材の活用や地域の人々との連携調整を行う。 ・全職員による指導体制を確立する。 | ・個人内評価を重視する。 ・発表会（異学年交流も含む） を利用した評価を取り入れる。",
    "text_length": 2573,
    "file": "【守口小】⑤R8「総合的な学習の時間」全体計画_sanitized.xlsx",
    "ext": ".xlsx",
    "extract_ok": true
  },
  {
    "school": "庭窪中",
    "grades": [],
    "themes": [
      "地域",
      "国際",
      "平和",
      "人権",
      "食",
      "文化",
      "多文化",
      "情報"
    ],
    "info_keywords": [],
    "grade_themes": [],
    "raw_preview": "研究部《 各分野の指導目標・指導計画 》１９．平和教育・国際教育＜学校教育目標＞自ら学び他者と響き合い未来を切り拓く健やかな生徒の育成＜平和教育目標＞自他を尊重し合い、わが国の社会や文化に対する理解と愛情を深めるとともに、国際理解や国際協調の視点に立って、恒久平和を願い、国際社会に貢献する生徒をはぐくむため、平和教育の研究・実践・授業づくり・集団づくりをおこなっていく。また、各教科、道徳、総合的な学習の時間及び特別活動等、全教育活動を通して、系統立て、持続可能なカリキュラムデザインを構築する。□ 平和教育において、従来の「被害」の側面だけではなく、「加害」の側面にも触れるなど、多面的・多角的な見方・考え方を学ぶ機会を設定し、解決が困難な課題・対立に対して、自らの考えを構築していく力を身につける。□ 戦争を直接体験した世代がいなくなりつつある中で、どのように学び、どのように継承し、後世に伝えていくのか考える。□ 国家だけでなく、特定の集団や個人が引き起こすテロ行為が頻発する等、戦争自体のあり方が変化してきていることを正しく認識し、価値観のちがいを受け入れたうえで、自身が行動することができる資質を身につけることが できるよう、校外学習・宿泊学習等なども活用しながら系統立てたカリキュラム構築にむけた研究を実践する。＜国際理解教育目標＞国際感覚あふれる心豊かな生徒をはぐくむため、在日外国人教育および国際教育の研究・実践・授業づくり・集団づくりをおこなっていく。また、外国籍または外国にルーツを持つ生徒が、自分のルーツに対して、誇りをもって自己実現できるよう、学校全体でルーツのある児童・生徒の成育歴を正しく把握するとともに、生徒自身につながる言葉・文化・歴史等について学ぶことができる機会や日本語指導を保障していく。□ 世界の国々の文化、歴史を正しく認識し、日本とのつながりについて知る。□ 多様な文化や考え方、ならびに、すべての人々の人権を尊重する態度を身につける。□ 在日外国人が直面している問題や課題を正しく認識し、それらの課題を解決していく態度や知識・技能を身につける。□ 外国籍または外国にルーツを持つ生徒は、自分のルーツや家族を否定することなく\"\"自分らしく\"\"生きていけるよう、自分につながる言葉・文化・歴史等について学ぶ機会を保障する。＜本校での平和・国際教育で育成を目指す資質・能力（基礎的・汎用的能力）＞自分ごととしてとらえる（主体性）たがいの考えを尊重する（協働力）協働して課題解決する（問題解決力）ともに考え、創り上げる（創造力）＜各学年の重点目標と計画＞第１学年第２学年第３学年＜平和教育＞なぜ平和や戦争について学ぶのか考える戦時中の生活について知る ⇒ 校外学習(ピースおおさか)など戦争の「被害」と「加害」に ついて「正しく知る」 ⇒ 宿泊学習(貝塚)など<国際理解教育>○ 外国にルーツをもつ生徒の把握○ 校区小学校との情報交換世界について知り、自分の国とのちがいについて「正しく知る」<平和教育>○ 戦争の「被害」と「加害」に ついて「受け入れる」 ⇒ 原爆投下の是非沖縄戦について正しく知る ⇒ 戦後というが、必ずしも「平和」とは言い切れない実態があることを正しく知る。<国際理解教育>自分の国と身近な国や地域の関係について「受け入れる」異文化を通じ、自国の文化を見つめる外国にルーツをもつ人たちが日本に住むようになった歴史的背景を学ぶ(思いを聴いて知る)<平和教育>これからの戦争と平和について考える戦争の悲惨さ、平和の大切さを学び、語り継いでいくために必要なことはなにか考える(行動する)<国際理解教育>○ 自分の国と身近な国や地域の関係の現状や課題について知る○ たがいのちがいを認め合い、共に生きていくために自分たちができることはなにか考え、行動する。１年２年３年<平和教育>・小学校での広島についての学習のふり返り・なぜ平和や戦争について学ぶのか・大阪空襲について (大空襲と空襲のちがい・天王寺動物園と空襲) ⇒ピースおおさかでの現地学習⇒戦争の「加害」の側面の体験実習<国際理解教育>・国しらべ（言葉、食べ物、衣服、日本の文化とのちがい、マイフラッグの制作 など）・ゲストティーチャーによる講演・多文化体験ができる学習（いろんな国の遊びや音楽、外国の言葉で話す など）<平和教育>・守口と戦争について（守口市の戦時中のようすや空襲の被害）・沖縄戦の経緯 ・ひめゆり学徒隊 ・ガマ ・対馬丸 ・鉄血勤皇隊 ・沖縄慰霊の日 6.23 ・平和の詩<国際理解教育>・歴史学習などを通して、自分の国と身近な国や地域との関係について知る ・身近な差別について知る（生活や就職、結婚、社会保障、人権など） ・ゲストティーチャーによる講演 【体験的な学習の充実のために】⇒生野コリアタウン、ウトロ平和祈念館での現地学習<平和教育>・沖縄南部戦跡での現地学習（沖縄平和祈念公園、ひめゆり平和祈念資料館、ガマ、）・平和セレモニー・平和学習のまとめ<国際理解教育>・日本に住む在日外国人の現状について「正しく知る」→「外国人労働者」「外国人難民「多文化共生に向けての取り組み」 ・国際理解学習のまとめ",
    "text_length": 2170,
    "file": "【庭窪中】⑤-１総合　平和・国際理解 (1)_sanitized.docx",
    "ext": ".docx",
    "extract_ok": true
  },
  {
    "school": "庭窪中",
    "grades": [],
    "themes": [
      "人権",
      "情報"
    ],
    "info_keywords": [],
    "grade_themes": [],
    "raw_preview": "研究部《 各分野の指導目標・指導計画 》20. 人権教育＜学校教育目標＞自ら学び 他者と響きあい 未来を切り開く 健やかな生徒の育成＜人権教育目標＞自他のつがいを尊重しよりよい人間関係をめざすための集団づくり仲間づくりへの取り組みを進める。共に伸びる仲間づくりを目指す。＜本校での人権教育で育成を目指す資質・能力（基礎的・汎用的能力）＞集団作り他者理解学習いのちの学習自己実現＜各学年の重点目標と計画＞第１学年第２学年第３学年他者理解学習、集団理解、自己実現につながる一年に。いのちの学習から始める一年。いのちの学習「自分らしさと生き方」障がい理解学習「『ちがい』を知り、支えあって生きる」いのちの学習「自分の性を大切に」部落問題学習「人の痛みに共感し、差別の不合理性を再確認する」※部落問題学習についての補足：１９８４年１０月の卒業生による部落差別発言を謙虚に受け止め、差別を許さない実践力を持った生徒の育成に取り組むこと１年２年３年【内容】いのちの学習・多様な性の形を理解する。・氾濫する性情報の状況や性被害の実態を知り、その防止や対処の仕方を知る。より良い人間関係を築くための互いの理解。それを発端として人との付き合い方を学ぶ。【内容】他者理解学習（みんな違ってみんないい）・自分と違う他者について知る。・障がい、違いについて。・自分たち自身の間にある様々な違いへの自覚を深めつつ、お互いの人間としての共通性を再認識し、差別を捉える視点や、人権を尊重しよりよい学年を築こうとする力を育む。【内容】いのちの学習・性別による役割分担にとらわれず、自分らしい生き方について考える。・多様な性の形があることを知り、無意識の偏見や差別的な見方をしていないかを考える。・性情報の氾濫や性被害の実態を知り、その防止法や対処の仕方を知る。・より良い人間関係を築くために互いを理解し、自分の思いを伝えることの大切さを考える。人との付き合い方についても学ぶ。【内容】障がい理解学習・障がいについて正しく知る。・他者との「ちがい」や「よさ」を知り、強みや個性を生かして助け合うことの大切さを知る。・パラスポーツ体験【内容】いのちの学習・妊娠、中絶、避妊について正しい知識を持たせる。・自分を大切にし、性について正しく考え、選択（行動）する力の必要性、責任が伴うことを知る。・性感染症、エイズについて正しい知識、予防（対処）方法を知り、「ともに生きる」「大切にできる関係」は何かを考える。【内容】部落問題学習・現代も続く差別について知り、差別された人の痛みに共感させ、その不合理性を再確認する。・差別は差別をする側の問題であることを理解させ、自分の中の差別性を知る。",
    "text_length": 1124,
    "file": "【庭窪中】⑤-２総合　人権 _sanitized.docx",
    "ext": ".docx",
    "extract_ok": true
  },
  {
    "school": "庭窪小",
    "grades": [],
    "themes": [
      "地域",
      "環境",
      "国際",
      "福祉",
      "平和",
      "食",
      "文化",
      "伝統",
      "情報",
      "探究"
    ],
    "info_keywords": [
      "インターネット"
    ],
    "grade_themes": [],
    "raw_preview": "総合的な学習の時間 全体計画・地域の実態・児童の実態・保護者や地域の人々の願い・地域の実態・児童の実態・保護者や地域の人々の願い・日本国憲法・教育基本法・学校基本法・学習指導要領・府、市の教育方針・日本国憲法・教育基本法・学校基本法・学習指導要領・府、市の教育方針学校教育目標郷土を愛し、未来と世界へ羽ばたく人の育成学校教育目標郷土を愛し、未来と世界へ羽ばたく人の育成＜めざす子ども像＞・元気に挨拶のできる子・仲良く助け合う子・自ら学習する子＜めざす子ども像＞・元気に挨拶のできる子・仲良く助け合う子・自ら学習する子【総合的な学習の時間の目標】探究的な見方・考え方を働かせ，横断的・総合的な学習を行うことを通して，よりよく課題を解決し，自己の生き方を考えていくための資質・能力を次のとおり育成する。(1) 地域の自然や社会の人々について学習を通して、探究的な学習の過程において，課題の解決に必要な知識及び技能を身に付け，課題に関わる概念を形成し，探究的な学習のよさを理解するようにする。(2) 実社会や実生活の中から問いを見いだし，自ら課題を設定し，課題を解決するために情報を集め，整理・分析して，相手に応じてまとめたり、表現したりすることができるようにする。(3) 探究的な学習に主体的・協働的に取り組むとともに，持続可能な社会づくりへの意識を持ち、互いのよさを生かしながら，積極的に社会に参画しようとする態度を養う。【総合的な学習の時間の目標】探究的な見方・考え方を働かせ，横断的・総合的な学習を行うことを通して，よりよく課題を解決し，自己の生き方を考えていくための資質・能力を次のとおり育成する。(1) 地域の自然や社会の人々について学習を通して、探究的な学習の過程において，課題の解決に必要な知識及び技能を身に付け，課題に関わる概念を形成し，探究的な学習のよさを理解するようにする。(2) 実社会や実生活の中から問いを見いだし，自ら課題を設定し，課題を解決するために情報を集め，整理・分析して，相手に応じてまとめたり、表現したりすることができるようにする。(3) 探究的な学習に主体的・協働的に取り組むとともに，持続可能な社会づくりへの意識を持ち、互いのよさを生かしながら，積極的に社会に参画しようとする態度を養う。【育てようとする資質や能力及び態度】学習方法に関すること自分自身に関すること他者や社会とのかかわりに関すること・課題を設定し、見通しをもって計画を立てる。・必要な情報を収集し分析する。・相手や目的に応じて、わかりやすくまとめ、表現する。・自らの行為について意思決定し、課題の解決に向けて行動する。・自らの生活の在り方を見直し、実践する。・自己の将来を考え、夢や希望をもつ。・異なる意見や他者の考えを受け入れる。・他者と協同して課題を解決する。・身の回りの環境とのかかわりを考えて生活する。【 内 容 】学年３ 年４ 年５ 年６ 年テーマ地域理解・国際理解福祉環境・食平和教育・キャリア教育学習課題もっとしりたいにわくぼの町私⇔人 理解から共に生きるSave The Earth私たちの平和 ～過去・現在・未来～学習対象地域の伝統や文化地域に住む人地域にある様々な場所・もの障害のある人福祉体験支援する仕組みや人々世界や日本の自然遺産と環境過去の戦争インターネット上の情報平和への具体的な活動等学習の評価・ワークシート、ノート、作文、絵、レポート等の制作物・発表や話し合いの様子・子どもの自己評価や相互評価・活動状況の観察学習の評価・ワークシート、ノート、作文、絵、レポート等の制作物・発表や話し合いの様子・子どもの自己評価や相互評価・活動状況の観察指導体制・教職員が一体となった指導・公共機関との連携や外部人材の効果的活用・多目的室・図書室・PC教室等の活用と学年全体での指導を意識して行う指導体制・教職員が一体となった指導・公共機関との連携や外部人材の効果的活用・多目的室・図書室・PC教室等の活用と学年全体での指導を意識して行う指導方法・体験を通した情報収集・体験で獲得した情報の言語化・教科との関連的な指導の重視・グループによる共同的な学習活動の充実指導方法・体験を通した情報収集・体験で獲得した情報の言語化・教科との関連的な指導の重視・グループによる共同的な学習活動の充実学習活動・学年共通の探究課題と年間活動計画のもと、柔軟な学習活動の展開・多様な表現方法で学習の成果を表現する場を設定する。学習活動・学年共通の探究課題と年間活動計画のもと、柔軟な学習活動の展開・多様な表現方法で学習の成果を表現する場を設定する。",
    "text_length": 1924,
    "file": "【庭窪小】⑤「総合的な学習の時間」の全体計画_sanitized.docx",
    "ext": ".docx",
    "extract_ok": true
  },
  {
    "school": "梶中",
    "grades": [],
    "themes": [
      "地域",
      "環境",
      "福祉",
      "人権",
      "健康",
      "情報",
      "探究"
    ],
    "info_keywords": [
      "iPad",
      "プレゼン",
      "グラフ"
    ],
    "grade_themes": [],
    "raw_preview": "守口市立梶中学校 「総合的な学習の時間」全体計画 学校教育目標 | 「総合的な学習の時間」の指導目標 | 「総合的な学習の時間」で生徒につけたい力 ・コミュニケーション力 ・豊かな人権感覚と行動力 ・課題を発見しようとする力 ・表現力 ・情報リテラシー ・自ら学ぶ力 ・環境を大切にする力 「未来の展望をもちたくましく生きる人間」の育成 | ・自ら課題を身につけ解決する ・学ぶ喜びを身に付ける ・人間関係を学ぶ ・生き方を考える 読書の習慣を身につけ、豊かな人間性や社会性を育てるとともに、情報の集め方や生き方の基礎を学ぶ。 自らの課題に対して自ら学び、考え、その成果を発表することで問題解決能力をそだてる。 体験、観察、調査を通じて、学び方やものの考え方を身につけ、自主協同的な態度を養う。 1学年 | 2学年 | 3学年 主題（人権教育）（自然体験学習） | 主題（福祉学習）（自然体験学習） | 主題（進路学習）（自然体験学習） 自分と他者が共に生きているということを考え、思いやりの心や助け合いの意識を高める。 自分の生活を見通し、進んで環境を保全していこうとする態度を育成する。 | 福祉体験への取り組みを通して協力・勤労・地域について学ぶ。 自分の生活を見通し、進んで環境を保全していこうとする態度を育成する。 | 自分の将来に関心を深め、自らの生き方を考える。 自分の生活を見通し、進んで環境を保全していこうとする態度を育成する。 朝の読書タイム 読書に親しみ、読書の習慣を身に付け、１，２学年で統一した指導形態で取り組み、文字からの情報理解力を高める。 学習活動 | 指導方法 | 指導体制 ・グループで資料や課題の整理をさせる ・図書室やiPadを利用し情報を収集させる。 | 学習の評価 | ・学年・学校全体で指 新たな課題 | 評価の方法 | 導体制を構築する ・観察法 | ・地域の人材を活用す 表現的 | ・ポートフォリオ | る 活動 | ・見学・調査・実習・インタビューなどを通して課題を追求させる。 | ・レポート | ・公共施設（図書館な ・作文 | ど）との連携をはかる 体験的 | ・対話 活動 | ・発表会、新聞つくり、プレゼンテーションなどの発表の機会をつくる。 | ・自己評価 探究的 | ・他者評価 活動 | ・相互評価 ・地域の人材を活用する。 テーマを設定する 国 | 語 | 社ｋ | 会 | 数 | 学 | 理 | 科 | 音が | 楽 | 美 | 術 | 保 | 体 | 技 | 家 | 英 | 語 | 道 | 徳 | 特 | 活 各教科等の関連 | 発表力を養う | 考えをまとめる力を養う | 文章をまとめる力を養う | 読解力を養う | 調べまとめる力を養う | 資料を活用する力を養う | 社会の出来事に関心を持つ | 分析解析する力を養う | 計画的に考える力を養う | グラフを活用する力を養う | つける | 実験の課題を解決する力を身に | 様々な自然事象に興味を持つ | 発想を豊かにする | 表現する力を身につける | 他者と協力する力を養う | 健康な生き方について考える | 見つける | 多くの情報の中から必要な情報を | ける | コミュニケーションの基礎を身につ | 活動を通して道徳性を養う | 養う | 活動を通して自主性や社会性を",
    "text_length": 1412,
    "file": "【梶中】⑤総合的全体計画_sanitized.xlsx",
    "ext": ".xlsx",
    "extract_ok": true
  },
  {
    "school": "梶小",
    "grades": [],
    "themes": [],
    "info_keywords": [],
    "grade_themes": [],
    "raw_preview": "５．生活・総合教育 「生活科」「総合的な学習の時間」の全体計画",
    "text_length": 31,
    "file": "【梶小】⑤「総合全体計画」_sanitized.xlsx",
    "ext": ".xlsx",
    "extract_ok": false
  },
  {
    "school": "第一中",
    "grades": [],
    "themes": [],
    "info_keywords": [],
    "raw_preview": "",
    "file": "【第一中】⑤5_4_1 「総合的な学習の時間」全体計画_sanitized.pdf",
    "ext": ".pdf",
    "extract_ok": false
  },
  {
    "school": "藤田小",
    "grades": [],
    "themes": [],
    "info_keywords": [],
    "raw_preview": "",
    "file": "【藤田小】⑤総合的な学習全体計画_sanitized.xls",
    "ext": ".xls",
    "extract_ok": false
  },
  {
    "school": "金田小",
    "grades": [],
    "themes": [
      "地域",
      "健康",
      "情報",
      "探究"
    ],
    "info_keywords": [],
    "grade_themes": [],
    "raw_preview": "６.総合的な学習の時間（そうごう・金田）全体計画「21世紀を生き抜く力を育む」～健康で、仲よく、共に学び、自ら働く、自主的な子～≪めざす子ども像≫ ≪具体的な子どもの姿≫ ○健康と安全に努める子 ○元気よく進んで挨拶をする○生きる喜びを知り、助け合う子 ○友だちと仲よくする○学ぶ喜びを知り、自ら学習する子 ○自主的に勉強する○働く尊さを知る子 ○掃除をがんばる「21世紀を生き抜く力を育む」～健康で、仲よく、共に学び、自ら働く、自主的な子～≪めざす子ども像≫ ≪具体的な子どもの姿≫ ○健康と安全に努める子 ○元気よく進んで挨拶をする○生きる喜びを知り、助け合う子 ○友だちと仲よくする○学ぶ喜びを知り、自ら学習する子 ○自主的に勉強する○働く尊さを知る子 ○掃除をがんばる探究課題の解決を通して育成を目指す資質・能力学年中学年高学年課題の設定自分の生活や身近な地域の中から問いを見出し、課題を立てるより広い範囲についての課題を自分で立て、解決の方法や手順など、見通しをもって考える。情報の収集目的に応じて対象や手段を選択し、自分たちの身近なところから情報を集める。目的に応じて対象や手段を選択・工夫し、効率的に情報を収集したり、見通しをもって蓄積したりする。整理分析事実を捉えるために比較・分類・関連付けるなどして、情報を整理・分析する。考えるための技法や思考ツールを効果的に用いて情報を整理・分析し、課題に即して多面的に考察する判断材料とする。まとめ・表現自分の伝えたいことを明確にし、方法を工夫しながらまとめ・表現する。自分の意見や立場を明確にし、相手や目的に応じてわかりやすくまとめ・表現するとともに、学習の仕方を振り返り、他の学習や生活に生かす。",
    "text_length": 729,
    "file": "【金田小】⑤「総合的な学習の時間」の全体計画_sanitized.docx",
    "ext": ".docx",
    "extract_ok": true
  },
  {
    "school": "錦中",
    "grades": [],
    "themes": [
      "地域",
      "国際",
      "福祉",
      "平和",
      "人権",
      "文化",
      "情報"
    ],
    "info_keywords": [
      "情報モラル"
    ],
    "grade_themes": [],
    "raw_preview": "段落フォント 標準の表 リストなし ヘッダー ヘッダー フッター フッター 吹き出し 吹き出し 怃岄俾 帆還怆岄俾 帆怉岄俾 怍岄俾 ゴシック 創英角 游ゴシック 游明朝 、。々〉》」』】〕゛゜ゝゞ・ヽヾ 〈《「『【〔 総合的な学習全体計画 福田麻依 「総合的な学習の時間」全体計画 学校教育目標 自己を含めた、全てのものの生命を尊重する人間の育成 家庭・地域の願い 本校の生徒目標 生徒の実態 物事に感謝する子ども。 何事も最後まで頑張りぬく子ども。 相手の立場に立って、親切にする子ども。 謙虚な心、広い心で人と接する子ども。 物を大切にし、整理整頓のできる子どもに育ってほしい。 挨拶をよくすること 腰骨を立てること 時を守ること 掃除をよくすること 履物をそろえること 返事がはっきりできること 一小一中のため学年を越えての地域のつながりが深い。 日々の地道な活動を続ける粘り強さに欠ける。 あいさつができ、奉仕活動にも進んで参加することができる。 思いやりがあり、仲間を大切にすることができる。 「総合的な学習の時間」の学校としての基本目標 国際理解・福祉体験・キャリア学習・校外学習などの体験学習を通して自ら課題を見つけ、自ら学び主体的に判断し、よりよく問題を解決する資質や能力を育てる。 「総合的な学習の時間」の育成目標 資質・能力・態度 年 自ら課題を見つけ、自ら学び考え、主体的に判断できる資質や能力を育てる。 年 社会の様々な事象に目を向け自主的・主体的に関わり、実際に体験することを通し生き方を考えさせる。 年 生徒の「生きる力」を育てるため、自らの将来について考えられる判断力と知識を獲得する方法を身につけさせる。 今年度の取り組み ・全学年、週に 時間の総合の時間を設定するが、必要に応じて時間確保を行う。 年間を見通した継続的な取り組みを行う。 教科横断的な取り組みの導入 ・新学習指導要領の本旨に沿い、本校の総合的学習の現状と課題を見い出し、学びの柱づくりを行う。 総合的な学習 年間計画案 情報モラル教室 薬物乱用防止教室 交通安全教室 いのちの学習 情報モラル教室 福祉学習 平和学習 福祉体験実習 情報モラル教室 平和学習 修学旅行 沖縄方面 進路学習 文化発表会 体育大会 平和学習 文化発表会 体育大会 平和学習 人権学習 文化発表会 体育大会 進路学習 進路学習 福祉学習 国際理解学習 進路学習 いのちの学習 平和学習 いのちの学習 進路学習 人権学習 同和問題・進学・就職 螐箐濖 愀お漀 愀お漀 钠钠續 伡怫樆 崀熄帀熄愀 崀熄帀熄愀 崀熄帀熄愀 楍牣獯景 卍潗摲潄 捯浵湥 福田麻依 総合的な学習全体計画 タイトル 総合的な学習全体計画 総合的な学習全体計画",
    "text_length": 1154,
    "file": "【錦中】⑤ 総合的な学習の時間　全体計画_sanitized.doc",
    "ext": ".doc",
    "extract_ok": true
  },
  {
    "school": "錦小",
    "grades": [],
    "themes": [
      "地域",
      "環境",
      "国際",
      "福祉",
      "平和",
      "食",
      "文化",
      "情報",
      "プログラミング",
      "探究"
    ],
    "info_keywords": [
      "プログラミング",
      "データ"
    ],
    "grade_themes": [],
    "raw_preview": "【教師の願い】・自ら課題を見つけ、主体的に問題解決できる態度を高めたい。・地域の中に価値を見出し、夢と希望を持ってともに育ってほしい。学校の教育目標「自ら考え行動する子」深く考え、表現し、すすんで学ぶ子思いやりの心を持ち、互いに協力する子心身ともにたくましく、正しく判断できる子総合的な学習の時間 全体計画 【児童の実態】・素直で明るい・考えることが苦手・体験学習が好き【保護者の願い】・思いやりを持って行動してほしい・教育環境を整えてほしい・学力をつけてほしい重点目標自分の興味関心のあることから課題を見つけ、進んで調べたり、調べたことをまとめ、いろいろな方法でみんなに伝えたりして、友達とともに高め合う。地域の一員であることを自覚し、よりよい町づくりに向けて、積極的に行動できる子を育てる。プログラミング教育を通して、論理的思考力を育み、身近な問題の解決に主体的に取り組もうとする態度を育てる。教科等で学ぶ知識及び技能等をより確実に身に付けることができるようにする。学年３年４年探究課題わたしたちの町 （地域理解）ともに生きる （環境/福祉）知識及び技能地域の自然の素晴らしさやそれを守る人々の工夫が分かる。地域の環境の現状や環境を保全する人々の工夫や努力が分かる。情報を比較・分類するなど，探究の過程に応じた技能を身に付けている。思考力，判断力，表現力課題の設定自分の関心から地域についての課題を設定し，解決方法を考えて探究している。情報の収集目的に応じて調べる方法を決め、必要な情報を集めている。整理・分析課題における事実や関係を比較・分類したり、数量などの客観的事実に基づいた比較により、共通点や相違点を見付けている。まとめ表現相手や目的に応じてわかりやすくまとめ、表現している。振り返り学習したことをふり返り、自分の生活に生かそうとしている。学びに向かう力主体性課題の解決に向け、目的意識をもって意欲的に取り組んでいる。協働性課題解決に向けて、身近な人と力を合わせて探究活動に取り組んでいる。自己理解自分のよさや、自分にできることに気付いている。他者理解自分と異なる意見や考えがあることに気付き，相手の立場を理解する。社会参画自分と地域とのつながりに気付き，地域の活動に参加しようとしている。評価の観点学年５年６年探求活動テーマ日本と世界の産業・文化 （国際理解）未来をつくるのはわたしたち （平和/キャリア）知識及び技能日本と世界の文化や食について調べ，その良さや、違いが分かる。過去と現在から自分たちの生活との関わりが分かる。情報を比較・分類・関連付けるなど，探究の過程に応じた技能を身に付けている。思考力・判断力・表現力課題の設定課題を設定し，解決方法や手順を考え，見通しを持って探究している。情報の収集目的に応じて手段を選択し，情報を収集したり，必要な情報を選んだりしている。整理・分析課題における事実や関係と，整理した情報を関連付けたり，多面的に考察したりして理解し，多くの情報の中からその特徴を見付けている。まとめ表現相手や目的，意図に応じ，工夫してまとめ，表現している。振り返り学習の仕方をふり返り，学習や生活に生かそうとしている。学びに向かう力主体性課題意識をもって，自分なりの方法を工夫しながら探究活動に取り組んでいる。協働性課題解決に向けて，他者と協働して探究活動に取り組み，その大切さに気付いている。自己理解探究活動を通して，自分の生活を見直し、自己理解を深めている。他者理解異なる意見や他者の考えを受け入れ、尊重しながら、探究活動に取り組んでいる。社会参画探究活動を通して，自分と実生活・実社会の問題の解決に取り組もうとする。家庭・地域との連携・地域の人材（ボランティア）の学習活動への参加・・・人材のデータ・ベース化とその活用・地域への情報発信の場 ・・・学校だより、学年発表会、学習参観",
    "text_length": 1613,
    "file": "【錦小】⑤総合的な学習の時間　全体計画_sanitized.docx",
    "ext": ".docx",
    "extract_ok": true
  }
]